people_also_ask_it/__init__.py
people_also_ask_it/data_collector.py
people_also_ask_it/exceptions.py
people_also_ask_it/google.py
people_also_ask_it/parser.py
people_also_ask_it/tools.py
people_also_ask_it-0.2.dist-info/LICENSE
people_also_ask_it-0.2.dist-info/METADATA
people_also_ask_it-0.2.dist-info/WHEEL
people_also_ask_it-0.2.dist-info/top_level.txt
people_also_ask_it-0.2.dist-info/RECORD
